{
    "packages":[
	{
            "name":"ftduino",
            "maintainer":"Till Harbaum",
            "websiteURL":"https://github.com/harbaum/ftduino",
            "email":"ftduino@harbaum.org",
            "help":{
		"online":"https://github.com/harbaum/ftduino"
            },
            "platforms":[
		{
		    "name": "ftDuino",
		    "architecture": "avr",
		    "version": "0.0.1",
		    "category": "ftDuino",
		    "url": "https://raw.githubusercontent.com/harbaum/ftduino/master/releases/0.0.1/ftduino-0.0.1.zip",

		    "archiveFileName": "ftduino-0.0.1.zip",
		    "checksum": "SHA-256:4ff786f78e99417db38a5e63ad06c4a9ee6737399a1ae806414de6265763fbe2",
		    "size": "122290",
		    "help": {
			"online": "https://github.com/harbaum/ftduino/issues"
		    },
		    "boards": [
			{
			    "name": "ftDuino fischertechnik compatible controller"
			}
		    ]
		}
		
            ],
            "tools":[
	    ]
	}
    ]
}
